AMI/__init__.py
AMI/_version.py
AMI/data/speaker_diarization/dev.mdtm
AMI/data/speaker_diarization/dev.uem
AMI/data/speaker_diarization/trn.mdtm
AMI/data/speaker_diarization/trn.uem
AMI/data/speaker_diarization/tst.mdtm
AMI/data/speaker_diarization/tst.uem
AMI/data/speaker_spotting/dev.enrol.txt
AMI/data/speaker_spotting/dev.trial.txt
AMI/data/speaker_spotting/tst.enrol.txt
AMI/data/speaker_spotting/tst.trial.txt
pyannote.db.odessa.ami-1.0.dist-info/LICENSE
pyannote.db.odessa.ami-1.0.dist-info/METADATA
pyannote.db.odessa.ami-1.0.dist-info/WHEEL
pyannote.db.odessa.ami-1.0.dist-info/entry_points.txt
pyannote.db.odessa.ami-1.0.dist-info/top_level.txt
pyannote.db.odessa.ami-1.0.dist-info/RECORD
